pydra_core/__init__.py
pydra_core/common/__init__.py
pydra_core/common/common.py
pydra_core/common/enum.py
pydra_core/common/interpolate.py
pydra_core/common/probability.py
pydra_core/core/__init__.py
pydra_core/core/calculation.py
pydra_core/core/exceedance_frequency_line.py
pydra_core/core/exceedance_frequency_line_experimental.py
pydra_core/core/hbn.py
pydra_core/core/datamodels/__init__.py
pydra_core/core/datamodels/frequency_line.py
pydra_core/data/settings/calculation_settings.sqlite
pydra_core/data/settings/lower_river_settings.cpg
pydra_core/data/settings/lower_river_settings.dbf
pydra_core/data/settings/lower_river_settings.prj
pydra_core/data/settings/lower_river_settings.shp
pydra_core/data/settings/lower_river_settings.shx
pydra_core/data/statistics/Afvoer/Borgharen/Ovkans_Borgharen_piekafvoer_2017.txt
pydra_core/data/statistics/Afvoer/Borgharen/Ovkans_Borgharen_piekafvoer_2017_metOnzHeid.txt
pydra_core/data/statistics/Afvoer/Borgharen/Ovkans_Borgharen_piekafvoer_OI2014_G_2015_metOnzHeid_v02.txt
pydra_core/data/statistics/Afvoer/Borgharen/Ovkans_Borgharen_piekafvoer_OI2014_G_2015_v02.txt
pydra_core/data/statistics/Afvoer/Borgharen/Ovkans_Borgharen_piekafvoer_OI2014_G_2050_metOnzHeid_v02.txt
pydra_core/data/statistics/Afvoer/Borgharen/Ovkans_Borgharen_piekafvoer_OI2014_G_2050_v02.txt
pydra_core/data/statistics/Afvoer/Borgharen/Ovkans_Borgharen_piekafvoer_OI2014_G_2100_metOnzHeid_v02.txt
pydra_core/data/statistics/Afvoer/Borgharen/Ovkans_Borgharen_piekafvoer_OI2014_G_2100_v02.txt
pydra_core/data/statistics/Afvoer/Borgharen/Ovkans_Borgharen_piekafvoer_OI2014_W_2015_metOnzHeid_v02.txt
pydra_core/data/statistics/Afvoer/Borgharen/Ovkans_Borgharen_piekafvoer_OI2014_W_2015_v02.txt
pydra_core/data/statistics/Afvoer/Borgharen/Ovkans_Borgharen_piekafvoer_OI2014_W_2050_metOnzHeid_v02.txt
pydra_core/data/statistics/Afvoer/Borgharen/Ovkans_Borgharen_piekafvoer_OI2014_W_2050_v02.txt
pydra_core-0.0.10.dist-info/METADATA
pydra_core-0.0.10.dist-info/WHEEL
pydra_core-0.0.10.dist-info/RECORD
