Metadata-Version: 2.4
Name: pydra_core
Version: 0.0.10
Summary: Python package for calculating hydraulic loads
Project-URL: Documentation, https://hkv-products-services.github.io/pydra_core/
Project-URL: Source, https://github.com/HKV-products-services/pydra_core
Author-email: Niels van der Vegt <n.vandervegt@hkv.nl>, David Haasnoot <d.haasnoot@hkv.nl>
License: GNU-GPL V3
Requires-Dist: fiona
Requires-Dist: matplotlib>=3.9.3
Requires-Dist: numpy
Requires-Dist: pandas
Requires-Dist: scipy
Requires-Dist: shapely
